py3_webpwn3r/__init__.py
py3_webpwn3r/core/__init__.py
py3_webpwn3r/core/costants.py
py3_webpwn3r/core/logging_config.py
py3_webpwn3r/core/run_copyr.py
py3_webpwn3r/core/run_scan.py
py3_webpwn3r/core/user_agent.py
py3_webpwn3r/core/vulnz.py
py3_webpwn3r-1.0.0.dist-info/LICENSE
py3_webpwn3r-1.0.0.dist-info/METADATA
py3_webpwn3r-1.0.0.dist-info/WHEEL
py3_webpwn3r-1.0.0.dist-info/top_level.txt
py3_webpwn3r-1.0.0.dist-info/RECORD
