Metadata-Version: 2.1
Name: py3-webpwn3r
Version: 1.0.0
Summary: Web Applications Security Scanner
Home-page: https://github.com/shadMod/py3-webpwn3r/
Download-URL: https://github.com/shadMod/py3-webpwn3r/archive/refs/tags/1.0.0.tar.gz
Author: shadMod
Author-email: support@shadmod.it
Project-URL: GitHub, https://github.com/shadMod/py3-webpwn3r/
Project-URL: Bug Tracker, https://github.com/shadMod/py3-webpwn3r/issues/
Keywords: WebPwn3r
Classifier: Development Status :: 4 - Beta
Classifier: Intended Audience :: Developers
Classifier: License :: OSI Approved :: GNU Affero General Public License v3
Classifier: Operating System :: OS Independent
Classifier: Programming Language :: Python :: 3
Classifier: Programming Language :: Python :: 3.10
Classifier: Programming Language :: Python :: 3.11
Classifier: Programming Language :: Python :: 3.12
Requires-Python: >=3.10
License-File: LICENSE
